<?xml version="1.0" encoding="UTF-8"?>
<!DOCTYPE plist PUBLIC "-//Apple//DTD PLIST 1.0//EN" "http://www.apple.com/DTDs/PropertyList-1.0.dtd"/>

<plist version="1.0">
    <dict>
        <key>ROOT</key>
        <array>
            <dict>
                <key>id</key>
                <string>27248</string>
                <key>className</key>
                <string>PTModelObjectCharacterSelector</string>
                <key>Name</key>
                <dict>
                    <key>value</key>
                    <string>Multiple Unlock</string>
                </dict>
                <key>Position</key>
                <dict>
                    <key>value</key>
                    <string>{331.592,579.577}</string>
                </dict>
                <key>Scale</key>
                <dict>
                    <key>value</key>
                    <string>{1.000,1.000}</string>
                </dict>
                <key>Hidden</key>
                <dict>
                    <key>visible</key>
                    <string>0</string>
                </dict>
                <key>Locked</key>
                <dict>
                    <key>visible</key>
                    <string>0</string>
                </dict>
                <key>Label Name</key>
                <dict>
                    <key>selectedStringValue</key>
                    <string>2</string>
                </dict>
                <key>zDepth</key>
                <string>1000</string>
            </dict>
            <dict>
                <key>id</key>
                <string>27256</string>
                <key>className</key>
                <string>PTModelObjectCharacterSelector</string>
                <key>Name</key>
                <dict>
                    <key>value</key>
                    <string>Multiple Unlock</string>
                </dict>
                <key>Position</key>
                <dict>
                    <key>value</key>
                    <string>{323.090,636.260}</string>
                </dict>
                <key>Scale</key>
                <dict>
                    <key>value</key>
                    <string>{1.000,1.000}</string>
                </dict>
                <key>Hidden</key>
                <dict>
                    <key>visible</key>
                    <string>0</string>
                </dict>
                <key>Locked</key>
                <dict>
                    <key>visible</key>
                    <string>0</string>
                </dict>
                <key>Label Name</key>
                <dict>
                    <key>selectedStringValue</key>
                    <string>2</string>
                </dict>
                <key>zDepth</key>
                <string>1000</string>
            </dict>
            <dict>
                <key>id</key>
                <string>27258</string>
                <key>className</key>
                <string>PTModelObjectCharacterSelector</string>
                <key>Name</key>
                <dict>
                    <key>value</key>
                    <string>Multiple Unlock</string>
                </dict>
                <key>Position</key>
                <dict>
                    <key>value</key>
                    <string>{320.000,595.000}</string>
                </dict>
                <key>Scale</key>
                <dict>
                    <key>value</key>
                    <string>{10.381,3.145}</string>
                </dict>
                <key>Hidden</key>
                <dict>
                    <key>visible</key>
                    <string>0</string>
                </dict>
                <key>Locked</key>
                <dict>
                    <key>visible</key>
                    <string>0</string>
                </dict>
                <key>Label Visibility</key>
                <dict>
                    <key>value</key>
                    <string>0</string>
                </dict>
                <key>Label Vertical Spacing</key>
                <dict>
                    <key>value</key>
                    <string>1000.000000</string>
                </dict>
                <key>Label Name</key>
                <dict>
                    <key>visible</key>
                    <string>0</string>
                    <key>selectedStringValue</key>
                    <string>2</string>
                </dict>
                <key>Spread</key>
                <dict>
                    <key>value</key>
                    <string>165.000000</string>
                </dict>
                <key>zDepth</key>
                <string>11</string>
            </dict>
        </array>
    </dict>
</plist>
