<?xml version="1.0" encoding="UTF-8"?>
<!DOCTYPE plist PUBLIC "-//Apple//DTD PLIST 1.0//EN" "http://www.apple.com/DTDs/PropertyList-1.0.dtd"/>

<plist version="1.0">
    <dict>
        <key>ROOT</key>
        <array>
            <dict>
                <key>id</key>
                <string>270</string>
                <key>className</key>
                <string>PTModelAssetObstacle</string>
                <key>Name</key>
                <dict>
                    <key>value</key>
                    <string>default-tail</string>
                </dict>
                <key>Collision Shape</key>
                <dict>
                    <key>id</key>
                    <string>271</string>
                    <key>className</key>
                    <string>PTModelPolygon</string>
                    <key>Name</key>
                    <dict>
                        <key>value</key>
                        <string></string>
                    </dict>
                    <key>points</key>
                    <array>
                        <string>{-2.000000,-8.000000}</string>
                        <string>{2.000000,-8.000000}</string>
                        <string>{2.000000,10.000000}</string>
                        <string>{-2.000000,10.000000}</string>
                    </array>
                    <key>oneWayCollisionVector</key>
                    <string>{0.000000,0.000000}</string>
                    <key>shapeType</key>
                    <string>1</string>
                </dict>
            </dict>
            <dict>
                <key>id</key>
                <string>501</string>
                <key>className</key>
                <string>PTModelAssetObstacle</string>
                <key>Name</key>
                <dict>
                    <key>value</key>
                    <string>blue-crystal</string>
                </dict>
                <key>Collision Shape</key>
                <dict>
                    <key>id</key>
                    <string>502</string>
                    <key>className</key>
                    <string>PTModelPolygon</string>
                    <key>Name</key>
                    <dict>
                        <key>value</key>
                        <string></string>
                    </dict>
                    <key>points</key>
                    <array>
                        <string>{112.000000,-237.000000}</string>
                        <string>{109.000000,237.000000}</string>
                        <string>{-63.000000,175.000000}</string>
                        <string>{-105.750000,63.000000}</string>
                        <string>{-93.500000,-109.000000}</string>
                        <string>{-87.250000,-176.000000}</string>
                    </array>
                    <key>oneWayCollisionVector</key>
                    <string>{0.000000,0.000000}</string>
                    <key>shapeType</key>
                    <string>1</string>
                </dict>
            </dict>
            <dict>
                <key>id</key>
                <string>512</string>
                <key>className</key>
                <string>PTModelAssetObstacle</string>
                <key>Name</key>
                <dict>
                    <key>value</key>
                    <string>brown-rock</string>
                </dict>
                <key>Collision Shape</key>
                <dict>
                    <key>id</key>
                    <string>513</string>
                    <key>className</key>
                    <string>PTModelPolygon</string>
                    <key>Name</key>
                    <dict>
                        <key>value</key>
                        <string></string>
                    </dict>
                    <key>points</key>
                    <array>
                        <string>{-105.000000,-209.000000}</string>
                        <string>{41.000000,-221.000000}</string>
                        <string>{173.750000,-159.250000}</string>
                        <string>{234.500000,-50.500000}</string>
                        <string>{164.000000,128.000000}</string>
                        <string>{51.000000,221.500000}</string>
                        <string>{-178.500000,161.250000}</string>
                        <string>{-247.000000,50.000000}</string>
                    </array>
                    <key>oneWayCollisionVector</key>
                    <string>{0.000000,0.000000}</string>
                    <key>shapeType</key>
                    <string>1</string>
                </dict>
            </dict>
            <dict>
                <key>id</key>
                <string>523</string>
                <key>className</key>
                <string>PTModelAssetObstacle</string>
                <key>Name</key>
                <dict>
                    <key>value</key>
                    <string>pink-crystal</string>
                </dict>
                <key>Collision Shape</key>
                <dict>
                    <key>id</key>
                    <string>524</string>
                    <key>className</key>
                    <string>PTModelPolygon</string>
                    <key>Name</key>
                    <dict>
                        <key>value</key>
                        <string></string>
                    </dict>
                    <key>points</key>
                    <array>
                        <string>{-76.000000,-148.000000}</string>
                        <string>{-7.000000,-217.000000}</string>
                        <string>{108.000000,-192.000000}</string>
                        <string>{87.000000,220.000000}</string>
                        <string>{-18.500000,163.500000}</string>
                        <string>{-87.000000,121.000000}</string>
                        <string>{-96.500000,11.500000}</string>
                    </array>
                    <key>oneWayCollisionVector</key>
                    <string>{0.000000,0.000000}</string>
                    <key>shapeType</key>
                    <string>1</string>
                </dict>
            </dict>
            <dict>
                <key>id</key>
                <string>534</string>
                <key>className</key>
                <string>PTModelAssetObstacle</string>
                <key>Name</key>
                <dict>
                    <key>value</key>
                    <string>Black Rock</string>
                </dict>
                <key>Collision Shape</key>
                <dict>
                    <key>id</key>
                    <string>535</string>
                    <key>className</key>
                    <string>PTModelPolygon</string>
                    <key>Name</key>
                    <dict>
                        <key>value</key>
                        <string></string>
                    </dict>
                    <key>points</key>
                    <array>
                        <string>{-118.000000,-25.000000}</string>
                        <string>{-70.000000,-83.000000}</string>
                        <string>{-36.000000,-100.500000}</string>
                        <string>{36.500000,-110.750000}</string>
                        <string>{118.250000,-52.875000}</string>
                        <string>{107.000000,112.000000}</string>
                        <string>{-11.000000,95.000000}</string>
                        <string>{-65.000000,40.000000}</string>
                    </array>
                    <key>oneWayCollisionVector</key>
                    <string>{0.000000,0.000000}</string>
                    <key>shapeType</key>
                    <string>1</string>
                </dict>
            </dict>
            <dict>
                <key>id</key>
                <string>603</string>
                <key>className</key>
                <string>PTModelAssetObstacle</string>
                <key>Name</key>
                <dict>
                    <key>value</key>
                    <string>bomb</string>
                </dict>
                <key>Collision Shape</key>
                <dict>
                    <key>id</key>
                    <string>643</string>
                    <key>className</key>
                    <string>PTModelCircle</string>
                    <key>Name</key>
                    <dict>
                        <key>value</key>
                        <string></string>
                    </dict>
                    <key>points</key>
                    <array>
                        <string>{0.000000,1.000000}</string>
                        <string>{45.799999,0.000000}</string>
                    </array>
                    <key>oneWayCollisionVector</key>
                    <string>{0.000000,0.000000}</string>
                    <key>shapeType</key>
                    <string>2</string>
                </dict>
            </dict>
            <dict>
                <key>id</key>
                <string>1334</string>
                <key>className</key>
                <string>PTModelAssetObstacle</string>
                <key>Name</key>
                <dict>
                    <key>value</key>
                    <string>spike-gate</string>
                </dict>
                <key>Collision Shape</key>
                <dict>
                    <key>id</key>
                    <string>1335</string>
                    <key>className</key>
                    <string>PTModelPolygon</string>
                    <key>Name</key>
                    <dict>
                        <key>value</key>
                        <string></string>
                    </dict>
                    <key>points</key>
                    <array>
                        <string>{-206.000000,-16.000000}</string>
                        <string>{204.000000,-31.000000}</string>
                        <string>{204.000000,53.000000}</string>
                        <string>{-203.000000,47.000000}</string>
                    </array>
                    <key>oneWayCollisionVector</key>
                    <string>{0.000000,0.000000}</string>
                    <key>shapeType</key>
                    <string>1</string>
                </dict>
            </dict>
            <dict>
                <key>id</key>
                <string>2125</string>
                <key>className</key>
                <string>PTModelAssetObstacle</string>
                <key>Name</key>
                <dict>
                    <key>value</key>
                    <string>laser-barrier-0001</string>
                </dict>
                <key>Collision Shape</key>
                <dict>
                    <key>id</key>
                    <string>2126</string>
                    <key>className</key>
                    <string>PTModelPolygon</string>
                    <key>Name</key>
                    <dict>
                        <key>value</key>
                        <string></string>
                    </dict>
                    <key>points</key>
                    <array>
                        <string>{-98.000000,-19.000000}</string>
                        <string>{-77.500000,-37.000000}</string>
                        <string>{35.000000,-55.000000}</string>
                        <string>{65.000000,-30.000000}</string>
                        <string>{64.500000,34.000000}</string>
                        <string>{31.000000,54.000000}</string>
                        <string>{-73.750000,40.500000}</string>
                        <string>{-96.500000,17.000000}</string>
                    </array>
                    <key>oneWayCollisionVector</key>
                    <string>{0.000000,0.000000}</string>
                    <key>shapeType</key>
                    <string>1</string>
                </dict>
            </dict>
            <dict>
                <key>id</key>
                <string>2138</string>
                <key>className</key>
                <string>PTModelAssetObstacle</string>
                <key>Name</key>
                <dict>
                    <key>value</key>
                    <string>laser-short-pink</string>
                </dict>
                <key>Collision Shape</key>
                <dict>
                    <key>id</key>
                    <string>14775</string>
                    <key>className</key>
                    <string>PTModelPolygon</string>
                    <key>Name</key>
                    <dict>
                        <key>value</key>
                        <string></string>
                    </dict>
                    <key>points</key>
                    <array>
                        <string>{-18.000000,-22.000000}</string>
                        <string>{19.000000,-22.000000}</string>
                        <string>{19.000000,26.000000}</string>
                        <string>{-19.000000,25.000000}</string>
                    </array>
                    <key>oneWayCollisionVector</key>
                    <string>{0.000000,0.000000}</string>
                    <key>shapeType</key>
                    <string>1</string>
                </dict>
            </dict>
            <dict>
                <key>id</key>
                <string>2313</string>
                <key>className</key>
                <string>PTModelAssetObstacle</string>
                <key>Name</key>
                <dict>
                    <key>value</key>
                    <string>yellow-rock</string>
                </dict>
                <key>Collision Shape</key>
                <dict>
                    <key>id</key>
                    <string>2314</string>
                    <key>className</key>
                    <string>PTModelPolygon</string>
                    <key>Name</key>
                    <dict>
                        <key>value</key>
                        <string></string>
                    </dict>
                    <key>points</key>
                    <array>
                        <string>{-122.000000,-24.000000}</string>
                        <string>{-72.000000,-84.000000}</string>
                        <string>{-40.000000,-101.000000}</string>
                        <string>{36.000000,-110.000000}</string>
                        <string>{121.000000,-52.500000}</string>
                        <string>{105.000000,109.000000}</string>
                        <string>{-14.500000,93.000000}</string>
                        <string>{-62.000000,46.000000}</string>
                    </array>
                    <key>oneWayCollisionVector</key>
                    <string>{0.000000,0.000000}</string>
                    <key>shapeType</key>
                    <string>1</string>
                </dict>
            </dict>
            <dict>
                <key>id</key>
                <string>3021</string>
                <key>className</key>
                <string>PTModelAssetObstacle</string>
                <key>Name</key>
                <dict>
                    <key>value</key>
                    <string>Cannon Laser</string>
                </dict>
                <key>Collision Shape</key>
                <dict>
                    <key>id</key>
                    <string>3022</string>
                    <key>className</key>
                    <string>PTModelPolygon</string>
                    <key>Name</key>
                    <dict>
                        <key>value</key>
                        <string></string>
                    </dict>
                    <key>points</key>
                    <array>
                        <string>{-99.000000,-52.000000}</string>
                        <string>{90.000000,-52.000000}</string>
                        <string>{90.000000,55.000000}</string>
                        <string>{-99.000000,55.000000}</string>
                    </array>
                    <key>oneWayCollisionVector</key>
                    <string>{0.000000,0.000000}</string>
                    <key>shapeType</key>
                    <string>1</string>
                </dict>
            </dict>
            <dict>
                <key>id</key>
                <string>3175</string>
                <key>className</key>
                <string>PTModelAssetObstacle</string>
                <key>Name</key>
                <dict>
                    <key>value</key>
                    <string>Pink ray</string>
                </dict>
                <key>Collision Shape</key>
                <dict>
                    <key>id</key>
                    <string>3211</string>
                    <key>className</key>
                    <string>PTModelPolygon</string>
                    <key>Name</key>
                    <dict>
                        <key>value</key>
                        <string></string>
                    </dict>
                    <key>points</key>
                    <array>
                        <string>{-149.000000,-11.000000}</string>
                        <string>{147.000000,-12.000000}</string>
                        <string>{148.000000,13.000000}</string>
                        <string>{-150.000000,12.000000}</string>
                    </array>
                    <key>oneWayCollisionVector</key>
                    <string>{0.000000,0.000000}</string>
                    <key>shapeType</key>
                    <string>1</string>
                </dict>
            </dict>
            <dict>
                <key>id</key>
                <string>4859</string>
                <key>className</key>
                <string>PTModelAssetObstacle</string>
                <key>Name</key>
                <dict>
                    <key>value</key>
                    <string>smash-it</string>
                </dict>
                <key>Collision Shape</key>
                <dict>
                    <key>id</key>
                    <string>4860</string>
                    <key>className</key>
                    <string>PTModelPolygon</string>
                    <key>Name</key>
                    <dict>
                        <key>value</key>
                        <string></string>
                    </dict>
                    <key>points</key>
                    <array>
                        <string>{-194.000000,-54.000000}</string>
                        <string>{194.000000,-54.000000}</string>
                        <string>{194.000000,55.000000}</string>
                        <string>{-194.000000,55.000000}</string>
                    </array>
                    <key>oneWayCollisionVector</key>
                    <string>{0.000000,0.000000}</string>
                    <key>shapeType</key>
                    <string>1</string>
                </dict>
            </dict>
            <dict>
                <key>id</key>
                <string>5000</string>
                <key>className</key>
                <string>PTModelAssetObstacle</string>
                <key>Name</key>
                <dict>
                    <key>value</key>
                    <string>support-start</string>
                </dict>
                <key>Collision Shape</key>
                <dict>
                    <key>id</key>
                    <string>5001</string>
                    <key>className</key>
                    <string>PTModelPolygon</string>
                    <key>Name</key>
                    <dict>
                        <key>value</key>
                        <string></string>
                    </dict>
                    <key>points</key>
                    <array>
                        <string>{-20.000000,-10.000000}</string>
                        <string>{20.000000,-10.000000}</string>
                        <string>{20.000000,-6.000000}</string>
                        <string>{-20.000000,-6.000000}</string>
                    </array>
                    <key>oneWayCollisionVector</key>
                    <string>{0.000000,0.000000}</string>
                    <key>shapeType</key>
                    <string>1</string>
                </dict>
            </dict>
            <dict>
                <key>id</key>
                <string>5081</string>
                <key>className</key>
                <string>PTModelAssetObstacle</string>
                <key>Name</key>
                <dict>
                    <key>value</key>
                    <string>tap-right-001</string>
                </dict>
                <key>Collision Shape</key>
                <dict>
                    <key>id</key>
                    <string>5082</string>
                    <key>className</key>
                    <string>PTModelPolygon</string>
                    <key>Name</key>
                    <dict>
                        <key>value</key>
                        <string></string>
                    </dict>
                    <key>points</key>
                    <array>
                        <string>{-65.000000,-65.000000}</string>
                        <string>{66.000000,-65.000000}</string>
                        <string>{66.000000,66.000000}</string>
                        <string>{-65.000000,66.000000}</string>
                    </array>
                    <key>oneWayCollisionVector</key>
                    <string>{0.000000,0.000000}</string>
                    <key>shapeType</key>
                    <string>1</string>
                </dict>
            </dict>
            <dict>
                <key>id</key>
                <string>5097</string>
                <key>className</key>
                <string>PTModelAssetObstacle</string>
                <key>Name</key>
                <dict>
                    <key>value</key>
                    <string>tap-left-001</string>
                </dict>
                <key>Collision Shape</key>
                <dict>
                    <key>id</key>
                    <string>5098</string>
                    <key>className</key>
                    <string>PTModelPolygon</string>
                    <key>Name</key>
                    <dict>
                        <key>value</key>
                        <string></string>
                    </dict>
                    <key>points</key>
                    <array>
                        <string>{-65.000000,-65.000000}</string>
                        <string>{66.000000,-65.000000}</string>
                        <string>{66.000000,66.000000}</string>
                        <string>{-65.000000,66.000000}</string>
                    </array>
                    <key>oneWayCollisionVector</key>
                    <string>{0.000000,0.000000}</string>
                    <key>shapeType</key>
                    <string>1</string>
                </dict>
            </dict>
            <dict>
                <key>id</key>
                <string>6380</string>
                <key>className</key>
                <string>PTModelAssetObstacle</string>
                <key>Name</key>
                <dict>
                    <key>value</key>
                    <string>cardume-0001</string>
                </dict>
                <key>Collision Shape</key>
                <dict>
                    <key>id</key>
                    <string>6381</string>
                    <key>className</key>
                    <string>PTModelPolygon</string>
                    <key>Name</key>
                    <dict>
                        <key>value</key>
                        <string></string>
                    </dict>
                    <key>points</key>
                    <array>
                        <string>{-38.000000,-47.000000}</string>
                        <string>{47.000000,-46.000000}</string>
                        <string>{32.000000,49.000000}</string>
                        <string>{-75.000000,65.000000}</string>
                    </array>
                    <key>oneWayCollisionVector</key>
                    <string>{0.000000,0.000000}</string>
                    <key>shapeType</key>
                    <string>1</string>
                </dict>
            </dict>
            <dict>
                <key>id</key>
                <string>7071</string>
                <key>className</key>
                <string>PTModelAssetObstacle</string>
                <key>Name</key>
                <dict>
                    <key>value</key>
                    <string>golden-arc-0001</string>
                </dict>
                <key>Collision Shape</key>
                <dict>
                    <key>id</key>
                    <string>7072</string>
                    <key>className</key>
                    <string>PTModelPolygon</string>
                    <key>Name</key>
                    <dict>
                        <key>value</key>
                        <string></string>
                    </dict>
                    <key>points</key>
                    <array>
                        <string>{-233.000000,-199.000000}</string>
                        <string>{234.000000,-199.000000}</string>
                        <string>{234.000000,206.000000}</string>
                        <string>{-233.000000,206.000000}</string>
                    </array>
                    <key>oneWayCollisionVector</key>
                    <string>{0.000000,0.000000}</string>
                    <key>shapeType</key>
                    <string>1</string>
                </dict>
            </dict>
            <dict>
                <key>id</key>
                <string>7085</string>
                <key>className</key>
                <string>PTModelAssetObstacle</string>
                <key>Name</key>
                <dict>
                    <key>value</key>
                    <string>light-arc-0001</string>
                </dict>
                <key>Collision Shape</key>
                <dict>
                    <key>id</key>
                    <string>7086</string>
                    <key>className</key>
                    <string>PTModelPolygon</string>
                    <key>Name</key>
                    <dict>
                        <key>value</key>
                        <string></string>
                    </dict>
                    <key>points</key>
                    <array>
                        <string>{-75.000000,-75.000000}</string>
                        <string>{77.000000,-75.000000}</string>
                        <string>{77.000000,77.000000}</string>
                        <string>{-75.000000,77.000000}</string>
                    </array>
                    <key>oneWayCollisionVector</key>
                    <string>{0.000000,0.000000}</string>
                    <key>shapeType</key>
                    <string>1</string>
                </dict>
            </dict>
            <dict>
                <key>id</key>
                <string>7151</string>
                <key>className</key>
                <string>PTModelAssetObstacle</string>
                <key>Name</key>
                <dict>
                    <key>value</key>
                    <string>arc-mask</string>
                </dict>
                <key>Collision Shape</key>
                <dict>
                    <key>id</key>
                    <string>7152</string>
                    <key>className</key>
                    <string>PTModelPolygon</string>
                    <key>Name</key>
                    <dict>
                        <key>value</key>
                        <string></string>
                    </dict>
                    <key>points</key>
                    <array>
                        <string>{-39.000000,3.000000}</string>
                        <string>{4.000000,-38.000000}</string>
                        <string>{26.000000,-8.500000}</string>
                        <string>{41.000000,23.000000}</string>
                        <string>{-17.000000,40.000000}</string>
                    </array>
                    <key>oneWayCollisionVector</key>
                    <string>{0.000000,0.000000}</string>
                    <key>shapeType</key>
                    <string>1</string>
                </dict>
            </dict>
            <dict>
                <key>id</key>
                <string>7720</string>
                <key>className</key>
                <string>PTModelAssetObstacle</string>
                <key>Name</key>
                <dict>
                    <key>value</key>
                    <string>helice-0001</string>
                </dict>
                <key>Collision Shape</key>
                <dict>
                    <key>id</key>
                    <string>7729</string>
                    <key>className</key>
                    <string>PTModelCircle</string>
                    <key>Name</key>
                    <dict>
                        <key>value</key>
                        <string></string>
                    </dict>
                    <key>points</key>
                    <array>
                        <string>{1.500000,1.500000}</string>
                        <string>{83.500000,-5.500000}</string>
                    </array>
                    <key>oneWayCollisionVector</key>
                    <string>{0.000000,0.000000}</string>
                    <key>shapeType</key>
                    <string>2</string>
                </dict>
            </dict>
            <dict>
                <key>id</key>
                <string>11268</string>
                <key>className</key>
                <string>PTModelAssetObstacle</string>
                <key>Name</key>
                <dict>
                    <key>value</key>
                    <string>triangle-laser-001</string>
                </dict>
                <key>Collision Shape</key>
                <dict>
                    <key>id</key>
                    <string>11269</string>
                    <key>className</key>
                    <string>PTModelPolygon</string>
                    <key>Name</key>
                    <dict>
                        <key>value</key>
                        <string></string>
                    </dict>
                    <key>points</key>
                    <array>
                        <string>{-71.000000,-10.000000}</string>
                        <string>{32.000000,-85.000000}</string>
                        <string>{46.000000,-76.000000}</string>
                        <string>{54.000000,-55.000000}</string>
                        <string>{51.500000,56.500000}</string>
                        <string>{45.750000,74.250000}</string>
                        <string>{30.000000,80.000000}</string>
                        <string>{-70.500000,4.000000}</string>
                    </array>
                    <key>oneWayCollisionVector</key>
                    <string>{0.000000,0.000000}</string>
                    <key>shapeType</key>
                    <string>1</string>
                </dict>
            </dict>
            <dict>
                <key>id</key>
                <string>11281</string>
                <key>className</key>
                <string>PTModelAssetObstacle</string>
                <key>Name</key>
                <dict>
                    <key>value</key>
                    <string>triangle-laser-bullet</string>
                </dict>
                <key>Collision Shape</key>
                <dict>
                    <key>id</key>
                    <string>11316</string>
                    <key>className</key>
                    <string>PTModelPolygon</string>
                    <key>Name</key>
                    <dict>
                        <key>value</key>
                        <string></string>
                    </dict>
                    <key>points</key>
                    <array>
                        <string>{-20.000000,-3.000000}</string>
                        <string>{22.000000,-3.000000}</string>
                        <string>{22.000000,5.000000}</string>
                        <string>{-20.000000,5.000000}</string>
                    </array>
                    <key>oneWayCollisionVector</key>
                    <string>{0.000000,0.000000}</string>
                    <key>shapeType</key>
                    <string>1</string>
                </dict>
            </dict>
            <dict>
                <key>id</key>
                <string>14731</string>
                <key>className</key>
                <string>PTModelAssetObstacle</string>
                <key>Name</key>
                <dict>
                    <key>value</key>
                    <string>rounded-spikes-chrome</string>
                </dict>
                <key>Collision Shape</key>
                <dict>
                    <key>id</key>
                    <string>14732</string>
                    <key>className</key>
                    <string>PTModelPolygon</string>
                    <key>Name</key>
                    <dict>
                        <key>value</key>
                        <string></string>
                    </dict>
                    <key>points</key>
                    <array>
                        <string>{-126.000000,-142.000000}</string>
                        <string>{136.000000,-132.000000}</string>
                        <string>{141.000000,106.000000}</string>
                        <string>{-50.000000,156.000000}</string>
                        <string>{-114.500000,36.500000}</string>
                    </array>
                    <key>oneWayCollisionVector</key>
                    <string>{0.000000,0.000000}</string>
                    <key>shapeType</key>
                    <string>1</string>
                </dict>
            </dict>
            <dict>
                <key>id</key>
                <string>15028</string>
                <key>className</key>
                <string>PTModelAssetObstacle</string>
                <key>Name</key>
                <dict>
                    <key>value</key>
                    <string>closed-gate</string>
                </dict>
                <key>Collision Shape</key>
                <dict>
                    <key>id</key>
                    <string>15029</string>
                    <key>className</key>
                    <string>PTModelPolygon</string>
                    <key>Name</key>
                    <dict>
                        <key>value</key>
                        <string></string>
                    </dict>
                    <key>points</key>
                    <array>
                        <string>{-247.000000,-88.000000}</string>
                        <string>{248.000000,-88.000000}</string>
                        <string>{248.000000,88.000000}</string>
                        <string>{-247.000000,88.000000}</string>
                    </array>
                    <key>oneWayCollisionVector</key>
                    <string>{0.000000,0.000000}</string>
                    <key>shapeType</key>
                    <string>1</string>
                </dict>
            </dict>
            <dict>
                <key>id</key>
                <string>15057</string>
                <key>className</key>
                <string>PTModelAssetObstacle</string>
                <key>Name</key>
                <dict>
                    <key>value</key>
                    <string>key-opens-the-gate</string>
                </dict>
                <key>Collision Shape</key>
                <dict>
                    <key>id</key>
                    <string>15067</string>
                    <key>className</key>
                    <string>PTModelCircle</string>
                    <key>Name</key>
                    <dict>
                        <key>value</key>
                        <string></string>
                    </dict>
                    <key>points</key>
                    <array>
                        <string>{0.500000,1.500000}</string>
                        <string>{63.900002,-11.500000}</string>
                    </array>
                    <key>oneWayCollisionVector</key>
                    <string>{0.000000,0.000000}</string>
                    <key>shapeType</key>
                    <string>2</string>
                </dict>
            </dict>
            <dict>
                <key>id</key>
                <string>15180</string>
                <key>className</key>
                <string>PTModelAssetObstacle</string>
                <key>Name</key>
                <dict>
                    <key>value</key>
                    <string>arrows-up-blinking-turbo-after-key</string>
                </dict>
                <key>Collision Shape</key>
                <dict>
                    <key>id</key>
                    <string>15181</string>
                    <key>className</key>
                    <string>PTModelPolygon</string>
                    <key>Name</key>
                    <dict>
                        <key>value</key>
                        <string></string>
                    </dict>
                    <key>points</key>
                    <array>
                        <string>{-31.000000,-29.000000}</string>
                        <string>{32.000000,-29.000000}</string>
                        <string>{32.000000,30.000000}</string>
                        <string>{-31.000000,30.000000}</string>
                    </array>
                    <key>oneWayCollisionVector</key>
                    <string>{0.000000,0.000000}</string>
                    <key>shapeType</key>
                    <string>1</string>
                </dict>
            </dict>
            <dict>
                <key>id</key>
                <string>16835</string>
                <key>className</key>
                <string>PTModelAssetObstacle</string>
                <key>Name</key>
                <dict>
                    <key>value</key>
                    <string>bolder-separator</string>
                </dict>
                <key>Collision Shape</key>
                <dict>
                    <key>id</key>
                    <string>16836</string>
                    <key>className</key>
                    <string>PTModelPolygon</string>
                    <key>Name</key>
                    <dict>
                        <key>value</key>
                        <string></string>
                    </dict>
                    <key>points</key>
                    <array>
                        <string>{-11.000000,-165.000000}</string>
                        <string>{77.000000,-118.000000}</string>
                        <string>{115.500000,0.500000}</string>
                        <string>{79.000000,145.000000}</string>
                        <string>{9.500000,153.000000}</string>
                        <string>{-70.000000,158.000000}</string>
                        <string>{-113.500000,81.500000}</string>
                        <string>{-80.250000,-97.750000}</string>
                    </array>
                    <key>oneWayCollisionVector</key>
                    <string>{0.000000,0.000000}</string>
                    <key>shapeType</key>
                    <string>1</string>
                </dict>
            </dict>
            <dict>
                <key>id</key>
                <string>17921</string>
                <key>className</key>
                <string>PTModelAssetObstacle</string>
                <key>Name</key>
                <dict>
                    <key>value</key>
                    <string>ball-pong-pink</string>
                </dict>
                <key>Collision Shape</key>
                <dict>
                    <key>id</key>
                    <string>17936</string>
                    <key>className</key>
                    <string>PTModelCircle</string>
                    <key>Name</key>
                    <dict>
                        <key>value</key>
                        <string></string>
                    </dict>
                    <key>points</key>
                    <array>
                        <string>{-1.000000,0.000000}</string>
                        <string>{13.400000,1.000000}</string>
                    </array>
                    <key>oneWayCollisionVector</key>
                    <string>{0.000000,0.000000}</string>
                    <key>shapeType</key>
                    <string>2</string>
                </dict>
            </dict>
            <dict>
                <key>id</key>
                <string>18123</string>
                <key>className</key>
                <string>PTModelAssetObstacle</string>
                <key>Name</key>
                <dict>
                    <key>value</key>
                    <string>killer-snake-head</string>
                </dict>
                <key>Collision Shape</key>
                <dict>
                    <key>id</key>
                    <string>18124</string>
                    <key>className</key>
                    <string>PTModelPolygon</string>
                    <key>Name</key>
                    <dict>
                        <key>value</key>
                        <string></string>
                    </dict>
                    <key>points</key>
                    <array>
                        <string>{-21.000000,-49.000000}</string>
                        <string>{21.000000,-50.000000}</string>
                        <string>{34.000000,59.000000}</string>
                        <string>{-34.000000,59.000000}</string>
                    </array>
                    <key>oneWayCollisionVector</key>
                    <string>{0.000000,0.000000}</string>
                    <key>shapeType</key>
                    <string>1</string>
                </dict>
            </dict>
            <dict>
                <key>id</key>
                <string>18134</string>
                <key>className</key>
                <string>PTModelAssetObstacle</string>
                <key>Name</key>
                <dict>
                    <key>value</key>
                    <string>killer-snake-body</string>
                </dict>
                <key>Collision Shape</key>
                <dict>
                    <key>id</key>
                    <string>18135</string>
                    <key>className</key>
                    <string>PTModelPolygon</string>
                    <key>Name</key>
                    <dict>
                        <key>value</key>
                        <string></string>
                    </dict>
                    <key>points</key>
                    <array>
                        <string>{-22.000000,-26.000000}</string>
                        <string>{23.000000,-26.000000}</string>
                        <string>{23.000000,27.000000}</string>
                        <string>{-22.000000,27.000000}</string>
                    </array>
                    <key>oneWayCollisionVector</key>
                    <string>{0.000000,0.000000}</string>
                    <key>shapeType</key>
                    <string>1</string>
                </dict>
            </dict>
            <dict>
                <key>id</key>
                <string>18175</string>
                <key>className</key>
                <string>PTModelAssetObstacle</string>
                <key>Name</key>
                <dict>
                    <key>value</key>
                    <string>ourico-0001</string>
                </dict>
                <key>Collision Shape</key>
                <dict>
                    <key>id</key>
                    <string>18204</string>
                    <key>className</key>
                    <string>PTModelCircle</string>
                    <key>Name</key>
                    <dict>
                        <key>value</key>
                        <string></string>
                    </dict>
                    <key>points</key>
                    <array>
                        <string>{1.000000,0.500000}</string>
                        <string>{46.000000,0.500000}</string>
                    </array>
                    <key>oneWayCollisionVector</key>
                    <string>{0.000000,0.000000}</string>
                    <key>shapeType</key>
                    <string>2</string>
                </dict>
            </dict>
            <dict>
                <key>id</key>
                <string>20246</string>
                <key>className</key>
                <string>PTModelAssetObstacle</string>
                <key>Name</key>
                <dict>
                    <key>value</key>
                    <string>proppeler</string>
                </dict>
                <key>Collision Shape</key>
                <dict>
                    <key>id</key>
                    <string>20256</string>
                    <key>className</key>
                    <string>PTModelPolygon</string>
                    <key>Name</key>
                    <dict>
                        <key>value</key>
                        <string></string>
                    </dict>
                    <key>points</key>
                    <array>
                        <string>{-35.000000,2.000000}</string>
                        <string>{35.000000,2.000000}</string>
                        <string>{21.000000,262.000000}</string>
                        <string>{-2.000000,288.000000}</string>
                        <string>{-24.000000,261.000000}</string>
                    </array>
                    <key>oneWayCollisionVector</key>
                    <string>{0.000000,0.000000}</string>
                    <key>shapeType</key>
                    <string>1</string>
                </dict>
            </dict>
            <dict>
                <key>id</key>
                <string>20599</string>
                <key>className</key>
                <string>PTModelAssetObstacle</string>
                <key>Name</key>
                <dict>
                    <key>value</key>
                    <string>black-gradient-side</string>
                </dict>
                <key>Collision Shape</key>
                <dict>
                    <key>id</key>
                    <string>20600</string>
                    <key>className</key>
                    <string>PTModelPolygon</string>
                    <key>Name</key>
                    <dict>
                        <key>value</key>
                        <string></string>
                    </dict>
                    <key>points</key>
                    <array>
                        <string>{-320.000000,-19.000000}</string>
                        <string>{-24.000000,-19.000000}</string>
                        <string>{-24.000000,20.000000}</string>
                        <string>{-320.000000,20.000000}</string>
                    </array>
                    <key>oneWayCollisionVector</key>
                    <string>{0.000000,0.000000}</string>
                    <key>shapeType</key>
                    <string>1</string>
                </dict>
            </dict>
            <dict>
                <key>id</key>
                <string>21827</string>
                <key>className</key>
                <string>PTModelAssetObstacle</string>
                <key>Name</key>
                <dict>
                    <key>value</key>
                    <string>laser-portal-0001</string>
                </dict>
                <key>Collision Shape</key>
                <dict>
                    <key>id</key>
                    <string>21828</string>
                    <key>className</key>
                    <string>PTModelPolygon</string>
                    <key>Name</key>
                    <dict>
                        <key>value</key>
                        <string></string>
                    </dict>
                    <key>points</key>
                    <array>
                        <string>{-64.000000,-45.000000}</string>
                        <string>{50.000000,-45.000000}</string>
                        <string>{50.000000,47.000000}</string>
                        <string>{-64.000000,47.000000}</string>
                    </array>
                    <key>oneWayCollisionVector</key>
                    <string>{0.000000,0.000000}</string>
                    <key>shapeType</key>
                    <string>1</string>
                </dict>
            </dict>
            <dict>
                <key>id</key>
                <string>21840</string>
                <key>className</key>
                <string>PTModelAssetObstacle</string>
                <key>Name</key>
                <dict>
                    <key>value</key>
                    <string>triple-laser-001</string>
                </dict>
                <key>Collision Shape</key>
                <dict>
                    <key>id</key>
                    <string>21841</string>
                    <key>className</key>
                    <string>PTModelPolygon</string>
                    <key>Name</key>
                    <dict>
                        <key>value</key>
                        <string></string>
                    </dict>
                    <key>points</key>
                    <array>
                        <string>{-275.000000,-25.000000}</string>
                        <string>{277.000000,-24.000000}</string>
                        <string>{278.000000,27.000000}</string>
                        <string>{-275.000000,25.000000}</string>
                    </array>
                    <key>oneWayCollisionVector</key>
                    <string>{0.000000,0.000000}</string>
                    <key>shapeType</key>
                    <string>1</string>
                </dict>
            </dict>
            <dict>
                <key>id</key>
                <string>21851</string>
                <key>className</key>
                <string>PTModelAssetObstacle</string>
                <key>Name</key>
                <dict>
                    <key>value</key>
                    <string>open-laser-portal</string>
                </dict>
                <key>Collision Shape</key>
                <dict>
                    <key>id</key>
                    <string>21852</string>
                    <key>className</key>
                    <string>PTModelPolygon</string>
                    <key>Name</key>
                    <dict>
                        <key>value</key>
                        <string></string>
                    </dict>
                    <key>points</key>
                    <array>
                        <string>{-45.000000,34.000000}</string>
                        <string>{-45.000000,-49.500000}</string>
                        <string>{45.000000,-49.000000}</string>
                        <string>{44.500000,35.000000}</string>
                        <string>{18.000000,51.000000}</string>
                        <string>{-21.000000,51.000000}</string>
                    </array>
                    <key>oneWayCollisionVector</key>
                    <string>{0.000000,0.000000}</string>
                    <key>shapeType</key>
                    <string>1</string>
                </dict>
            </dict>
            <dict>
                <key>id</key>
                <string>24420</string>
                <key>className</key>
                <string>PTModelAssetObstacle</string>
                <key>Name</key>
                <dict>
                    <key>value</key>
                    <string>trap-wall-01</string>
                </dict>
                <key>Collision Shape</key>
                <dict>
                    <key>id</key>
                    <string>24421</string>
                    <key>className</key>
                    <string>PTModelPolygon</string>
                    <key>Name</key>
                    <dict>
                        <key>value</key>
                        <string></string>
                    </dict>
                    <key>points</key>
                    <array>
                        <string>{-199.000000,-13.000000}</string>
                        <string>{-40.000000,-169.000000}</string>
                        <string>{197.000000,-169.000000}</string>
                        <string>{197.000000,169.000000}</string>
                        <string>{-20.000000,172.000000}</string>
                    </array>
                    <key>oneWayCollisionVector</key>
                    <string>{0.000000,0.000000}</string>
                    <key>shapeType</key>
                    <string>1</string>
                </dict>
            </dict>
            <dict>
                <key>id</key>
                <string>24435</string>
                <key>className</key>
                <string>PTModelAssetObstacle</string>
                <key>Name</key>
                <dict>
                    <key>value</key>
                    <string>trap-wall-support</string>
                </dict>
                <key>Collision Shape</key>
                <dict>
                    <key>id</key>
                    <string>24436</string>
                    <key>className</key>
                    <string>PTModelPolygon</string>
                    <key>Name</key>
                    <dict>
                        <key>value</key>
                        <string></string>
                    </dict>
                    <key>points</key>
                    <array>
                        <string>{-84.000000,-169.000000}</string>
                        <string>{85.000000,-169.000000}</string>
                        <string>{85.000000,169.000000}</string>
                        <string>{-84.000000,169.000000}</string>
                    </array>
                    <key>oneWayCollisionVector</key>
                    <string>{0.000000,0.000000}</string>
                    <key>shapeType</key>
                    <string>1</string>
                </dict>
            </dict>
            <dict>
                <key>id</key>
                <string>24501</string>
                <key>className</key>
                <string>PTModelAssetObstacle</string>
                <key>Name</key>
                <dict>
                    <key>value</key>
                    <string>trap-walls-open-01</string>
                </dict>
                <key>Collision Shape</key>
                <dict>
                    <key>id</key>
                    <string>24502</string>
                    <key>className</key>
                    <string>PTModelPolygon</string>
                    <key>Name</key>
                    <dict>
                        <key>value</key>
                        <string></string>
                    </dict>
                    <key>points</key>
                    <array>
                        <string>{-81.000000,-70.000000}</string>
                        <string>{82.000000,-70.000000}</string>
                        <string>{82.000000,71.000000}</string>
                        <string>{-81.000000,71.000000}</string>
                    </array>
                    <key>oneWayCollisionVector</key>
                    <string>{0.000000,0.000000}</string>
                    <key>shapeType</key>
                    <string>1</string>
                </dict>
            </dict>
            <dict>
                <key>id</key>
                <string>26600</string>
                <key>className</key>
                <string>PTModelAssetObstacle</string>
                <key>Name</key>
                <dict>
                    <key>value</key>
                    <string>red-crystal</string>
                </dict>
                <key>Collision Shape</key>
                <dict>
                    <key>id</key>
                    <string>26601</string>
                    <key>className</key>
                    <string>PTModelPolygon</string>
                    <key>Name</key>
                    <dict>
                        <key>value</key>
                        <string></string>
                    </dict>
                    <key>points</key>
                    <array>
                        <string>{-76.000000,-141.000000}</string>
                        <string>{-22.000000,-218.000000}</string>
                        <string>{112.000000,-241.000000}</string>
                        <string>{100.000000,166.000000}</string>
                        <string>{73.500000,216.500000}</string>
                        <string>{-83.000000,128.000000}</string>
                        <string>{-101.000000,53.500000}</string>
                        <string>{-98.500000,-89.750000}</string>
                    </array>
                    <key>oneWayCollisionVector</key>
                    <string>{0.000000,0.000000}</string>
                    <key>shapeType</key>
                    <string>1</string>
                </dict>
            </dict>
            <dict>
                <key>id</key>
                <string>32010</string>
                <key>className</key>
                <string>PTModelAssetObstacle</string>
                <key>Name</key>
                <dict>
                    <key>value</key>
                    <string>monster-fish-001</string>
                </dict>
                <key>Collision Shape</key>
                <dict>
                    <key>id</key>
                    <string>32011</string>
                    <key>className</key>
                    <string>PTModelPolygon</string>
                    <key>Name</key>
                    <dict>
                        <key>value</key>
                        <string></string>
                    </dict>
                    <key>points</key>
                    <array>
                        <string>{13.000000,-26.000000}</string>
                        <string>{66.000000,-15.500000}</string>
                        <string>{105.000000,25.000000}</string>
                        <string>{86.750000,60.750000}</string>
                        <string>{44.500000,79.500000}</string>
                        <string>{-24.750000,60.250000}</string>
                        <string>{-78.000000,27.000000}</string>
                    </array>
                    <key>oneWayCollisionVector</key>
                    <string>{0.000000,0.000000}</string>
                    <key>shapeType</key>
                    <string>1</string>
                </dict>
            </dict>
            <dict>
                <key>id</key>
                <string>32255</string>
                <key>className</key>
                <string>PTModelAssetObstacle</string>
                <key>Name</key>
                <dict>
                    <key>value</key>
                    <string>tentacle-nucleo</string>
                </dict>
                <key>Collision Shape</key>
                <dict>
                    <key>id</key>
                    <string>34093</string>
                    <key>className</key>
                    <string>PTModelPolygon</string>
                    <key>Name</key>
                    <dict>
                        <key>value</key>
                        <string></string>
                    </dict>
                    <key>points</key>
                    <array>
                        <string>{-72.000000,-78.000000}</string>
                        <string>{-1.000000,-91.500000}</string>
                        <string>{61.000000,-71.000000}</string>
                        <string>{96.000000,0.000000}</string>
                        <string>{51.000000,51.000000}</string>
                        <string>{-49.000000,52.000000}</string>
                        <string>{-98.000000,0.500000}</string>
                    </array>
                    <key>oneWayCollisionVector</key>
                    <string>{0.000000,0.000000}</string>
                    <key>shapeType</key>
                    <string>1</string>
                </dict>
            </dict>
            <dict>
                <key>id</key>
                <string>33086</string>
                <key>className</key>
                <string>PTModelAssetObstacle</string>
                <key>Name</key>
                <dict>
                    <key>value</key>
                    <string>big-rock-spiked</string>
                </dict>
                <key>Collision Shape</key>
                <dict>
                    <key>id</key>
                    <string>33087</string>
                    <key>className</key>
                    <string>PTModelPolygon</string>
                    <key>Name</key>
                    <dict>
                        <key>value</key>
                        <string></string>
                    </dict>
                    <key>points</key>
                    <array>
                        <string>{-64.000000,-109.000000}</string>
                        <string>{63.000000,-125.000000}</string>
                        <string>{103.000000,-79.000000}</string>
                        <string>{107.000000,26.000000}</string>
                        <string>{91.000000,98.000000}</string>
                        <string>{-10.500000,127.500000}</string>
                        <string>{-91.000000,90.000000}</string>
                        <string>{-101.000000,33.500000}</string>
                    </array>
                    <key>oneWayCollisionVector</key>
                    <string>{0.000000,0.000000}</string>
                    <key>shapeType</key>
                    <string>1</string>
                </dict>
            </dict>
            <dict>
                <key>id</key>
                <string>33173</string>
                <key>className</key>
                <string>PTModelAssetObstacle</string>
                <key>Name</key>
                <dict>
                    <key>value</key>
                    <string>big-rock-3</string>
                </dict>
                <key>Collision Shape</key>
                <dict>
                    <key>id</key>
                    <string>33174</string>
                    <key>className</key>
                    <string>PTModelPolygon</string>
                    <key>Name</key>
                    <dict>
                        <key>value</key>
                        <string></string>
                    </dict>
                    <key>points</key>
                    <array>
                        <string>{-114.000000,-69.000000}</string>
                        <string>{-73.000000,-111.500000}</string>
                        <string>{40.000000,-111.000000}</string>
                        <string>{116.000000,13.500000}</string>
                        <string>{45.000000,111.750000}</string>
                        <string>{-83.000000,67.000000}</string>
                        <string>{-116.000000,12.000000}</string>
                    </array>
                    <key>oneWayCollisionVector</key>
                    <string>{0.000000,0.000000}</string>
                    <key>shapeType</key>
                    <string>1</string>
                </dict>
            </dict>
            <dict>
                <key>id</key>
                <string>33405</string>
                <key>className</key>
                <string>PTModelAssetObstacle</string>
                <key>Name</key>
                <dict>
                    <key>value</key>
                    <string>spike-star-bullet</string>
                </dict>
                <key>Collision Shape</key>
                <dict>
                    <key>id</key>
                    <string>33406</string>
                    <key>className</key>
                    <string>PTModelPolygon</string>
                    <key>Name</key>
                    <dict>
                        <key>value</key>
                        <string></string>
                    </dict>
                    <key>points</key>
                    <array>
                        <string>{1.000000,-20.000000}</string>
                        <string>{6.000000,20.000000}</string>
                        <string>{0.000000,22.000000}</string>
                        <string>{-4.000000,20.000000}</string>
                    </array>
                    <key>oneWayCollisionVector</key>
                    <string>{0.000000,0.000000}</string>
                    <key>shapeType</key>
                    <string>1</string>
                </dict>
            </dict>
            <dict>
                <key>id</key>
                <string>36444</string>
                <key>className</key>
                <string>PTModelAssetObstacle</string>
                <key>Name</key>
                <dict>
                    <key>value</key>
                    <string>SFX Bubbles</string>
                </dict>
                <key>Collision Shape</key>
                <dict>
                    <key>id</key>
                    <string>36445</string>
                    <key>className</key>
                    <string>PTModelPolygon</string>
                    <key>Name</key>
                    <dict>
                        <key>value</key>
                        <string></string>
                    </dict>
                    <key>points</key>
                    <array>
                        <string>{-45.000000,-45.000000}</string>
                        <string>{46.000000,-45.000000}</string>
                        <string>{46.000000,46.000000}</string>
                        <string>{-45.000000,46.000000}</string>
                    </array>
                    <key>oneWayCollisionVector</key>
                    <string>{0.000000,0.000000}</string>
                    <key>shapeType</key>
                    <string>1</string>
                </dict>
            </dict>
            <dict>
                <key>id</key>
                <string>37831</string>
                <key>className</key>
                <string>PTModelAssetObstacle</string>
                <key>Name</key>
                <dict>
                    <key>value</key>
                    <string>base-chain</string>
                </dict>
                <key>Collision Shape</key>
                <dict>
                    <key>id</key>
                    <string>37832</string>
                    <key>className</key>
                    <string>PTModelPolygon</string>
                    <key>Name</key>
                    <dict>
                        <key>value</key>
                        <string></string>
                    </dict>
                    <key>points</key>
                    <array>
                        <string>{-23.000000,-13.000000}</string>
                        <string>{23.000000,-13.000000}</string>
                        <string>{23.000000,13.000000}</string>
                        <string>{-23.000000,13.000000}</string>
                    </array>
                    <key>oneWayCollisionVector</key>
                    <string>{0.000000,0.000000}</string>
                    <key>shapeType</key>
                    <string>1</string>
                </dict>
            </dict>
            <dict>
                <key>id</key>
                <string>37842</string>
                <key>className</key>
                <string>PTModelAssetObstacle</string>
                <key>Name</key>
                <dict>
                    <key>value</key>
                    <string>chain</string>
                </dict>
                <key>Collision Shape</key>
                <dict>
                    <key>id</key>
                    <string>37843</string>
                    <key>className</key>
                    <string>PTModelPolygon</string>
                    <key>Name</key>
                    <dict>
                        <key>value</key>
                        <string></string>
                    </dict>
                    <key>points</key>
                    <array>
                        <string>{-7.000000,-13.000000}</string>
                        <string>{8.000000,-13.000000}</string>
                        <string>{8.000000,14.000000}</string>
                        <string>{-7.000000,14.000000}</string>
                    </array>
                    <key>oneWayCollisionVector</key>
                    <string>{0.000000,0.000000}</string>
                    <key>shapeType</key>
                    <string>1</string>
                </dict>
            </dict>
            <dict>
                <key>id</key>
                <string>39298</string>
                <key>className</key>
                <string>PTModelAssetObstacle</string>
                <key>Name</key>
                <dict>
                    <key>value</key>
                    <string>mega-laser</string>
                </dict>
                <key>Collision Shape</key>
                <dict>
                    <key>id</key>
                    <string>39326</string>
                    <key>className</key>
                    <string>PTModelPolygon</string>
                    <key>Name</key>
                    <dict>
                        <key>value</key>
                        <string></string>
                    </dict>
                    <key>points</key>
                    <array>
                        <string>{-27.000000,-13.000000}</string>
                        <string>{27.000000,-13.000000}</string>
                        <string>{27.000000,14.000000}</string>
                        <string>{-27.000000,14.000000}</string>
                    </array>
                    <key>oneWayCollisionVector</key>
                    <string>{0.000000,0.000000}</string>
                    <key>shapeType</key>
                    <string>1</string>
                </dict>
            </dict>
            <dict>
                <key>id</key>
                <string>39409</string>
                <key>className</key>
                <string>PTModelAssetObstacle</string>
                <key>Name</key>
                <dict>
                    <key>value</key>
                    <string>mega-laser-cannon-001</string>
                </dict>
                <key>Collision Shape</key>
                <dict>
                    <key>id</key>
                    <string>39410</string>
                    <key>className</key>
                    <string>PTModelPolygon</string>
                    <key>Name</key>
                    <dict>
                        <key>value</key>
                        <string></string>
                    </dict>
                    <key>points</key>
                    <array>
                        <string>{-36.000000,-31.000000}</string>
                        <string>{43.000000,-31.000000}</string>
                        <string>{43.000000,38.000000}</string>
                        <string>{-36.000000,38.000000}</string>
                    </array>
                    <key>oneWayCollisionVector</key>
                    <string>{0.000000,0.000000}</string>
                    <key>shapeType</key>
                    <string>1</string>
                </dict>
            </dict>
            <dict>
                <key>id</key>
                <string>42543</string>
                <key>className</key>
                <string>PTModelAssetObstacle</string>
                <key>Name</key>
                <dict>
                    <key>value</key>
                    <string>invisible-killer</string>
                </dict>
                <key>Collision Shape</key>
                <dict>
                    <key>id</key>
                    <string>42544</string>
                    <key>className</key>
                    <string>PTModelPolygon</string>
                    <key>Name</key>
                    <dict>
                        <key>value</key>
                        <string></string>
                    </dict>
                    <key>points</key>
                    <array>
                        <string>{-5.000000,-550.000000}</string>
                        <string>{5.000000,-550.000000}</string>
                        <string>{5.000000,550.000000}</string>
                        <string>{-5.000000,550.000000}</string>
                    </array>
                    <key>oneWayCollisionVector</key>
                    <string>{0.000000,0.000000}</string>
                    <key>shapeType</key>
                    <string>1</string>
                </dict>
            </dict>
        </array>
    </dict>
</plist>
